<annotation>
  <folder>input</folder>
  <filename>20190331_165908.jpg</filename>
  <path>D:\Dvision\OpenLabeling\main\input\20190331_165908.jpg</path>
  <source>
    <database>Unknown</database>
  </source>
  <size>
    <width>1960</width>
    <height>4032</height>
    <depth>3</depth>
  </size>
  <segmented>0</segmented>
  <object>
    <name>d12_9</name>
    <pose>Unspecified</pose>
    <truncated>0</truncated>
    <difficult>0</difficult>
    <bndbox>
      <xmin>366</xmin>
      <ymin>73</ymin>
      <xmax>1328</xmax>
      <ymax>1150</ymax>
    </bndbox>
  </object>
  <object>
    <name>d12_9</name>
    <pose>Unspecified</pose>
    <truncated>0</truncated>
    <difficult>0</difficult>
    <bndbox>
      <xmin>415</xmin>
      <ymin>1491</ymin>
      <xmax>1366</xmax>
      <ymax>2480</ymax>
    </bndbox>
  </object>
  <object>
    <name>d12_9</name>
    <pose>Unspecified</pose>
    <truncated>0</truncated>
    <difficult>0</difficult>
    <bndbox>
      <xmin>395</xmin>
      <ymin>2977</ymin>
      <xmax>1344</xmax>
      <ymax>3944</ymax>
    </bndbox>
  </object>
</annotation>
