<annotation>
  <folder>input</folder>
  <filename>DSC_0200.JPG</filename>
  <path>/home/mauro/Workspace/DiceScanner/BBlabelTools/OpenLabeling-master/main/input/DSC_0200.JPG</path>
  <source>
    <database>Unknown</database>
  </source>
  <size>
    <width>3120</width>
    <height>4208</height>
    <depth>3</depth>
  </size>
  <segmented>0</segmented>
  <object>
    <name>d8</name>
    <pose>Unspecified</pose>
    <truncated>0</truncated>
    <difficult>0</difficult>
    <bndbox>
      <xmin>1629</xmin>
      <ymin>161</ymin>
      <xmax>2060</xmax>
      <ymax>682</ymax>
    </bndbox>
  </object>
  <object>
    <name>d8</name>
    <pose>Unspecified</pose>
    <truncated>0</truncated>
    <difficult>0</difficult>
    <bndbox>
      <xmin>947</xmin>
      <ymin>633</ymin>
      <xmax>1418</xmax>
      <ymax>1163</ymax>
    </bndbox>
  </object>
  <object>
    <name>d8</name>
    <pose>Unspecified</pose>
    <truncated>0</truncated>
    <difficult>0</difficult>
    <bndbox>
      <xmin>866</xmin>
      <ymin>1369</ymin>
      <xmax>1279</xmax>
      <ymax>1827</ymax>
    </bndbox>
  </object>
  <object>
    <name>d8</name>
    <pose>Unspecified</pose>
    <truncated>0</truncated>
    <difficult>0</difficult>
    <bndbox>
      <xmin>1894</xmin>
      <ymin>1145</ymin>
      <xmax>2374</xmax>
      <ymax>1567</ymax>
    </bndbox>
  </object>
  <object>
    <name>d8</name>
    <pose>Unspecified</pose>
    <truncated>0</truncated>
    <difficult>0</difficult>
    <bndbox>
      <xmin>2280</xmin>
      <ymin>1764</ymin>
      <xmax>2680</xmax>
      <ymax>2200</ymax>
    </bndbox>
  </object>
  <object>
    <name>d8</name>
    <pose>Unspecified</pose>
    <truncated>0</truncated>
    <difficult>0</difficult>
    <bndbox>
      <xmin>1405</xmin>
      <ymin>2088</ymin>
      <xmax>1849</xmax>
      <ymax>2483</ymax>
    </bndbox>
  </object>
  <object>
    <name>d8</name>
    <pose>Unspecified</pose>
    <truncated>0</truncated>
    <difficult>0</difficult>
    <bndbox>
      <xmin>718</xmin>
      <ymin>2362</ymin>
      <xmax>1099</xmax>
      <ymax>2779</ymax>
    </bndbox>
  </object>
  <object>
    <name>d8</name>
    <pose>Unspecified</pose>
    <truncated>0</truncated>
    <difficult>0</difficult>
    <bndbox>
      <xmin>1921</xmin>
      <ymin>2717</ymin>
      <xmax>2325</xmax>
      <ymax>3134</ymax>
    </bndbox>
  </object>
  <object>
    <name>d8</name>
    <pose>Unspecified</pose>
    <truncated>0</truncated>
    <difficult>0</difficult>
    <bndbox>
      <xmin>628</xmin>
      <ymin>3116</ymin>
      <xmax>1113</xmax>
      <ymax>3633</ymax>
    </bndbox>
  </object>
  <object>
    <name>d8</name>
    <pose>Unspecified</pose>
    <truncated>0</truncated>
    <difficult>0</difficult>
    <bndbox>
      <xmin>1557</xmin>
      <ymin>3588</ymin>
      <xmax>2011</xmax>
      <ymax>4145</ymax>
    </bndbox>
  </object>
</annotation>
