<annotation>
  <folder>input</folder>
  <filename>20190405_133514.jpg</filename>
  <path>D:\Dvision\OpenLabeling\main\input\20190405_133514.jpg</path>
  <source>
    <database>Unknown</database>
  </source>
  <size>
    <width>4032</width>
    <height>1960</height>
    <depth>3</depth>
  </size>
  <segmented>0</segmented>
  <object>
    <name>d10_3</name>
    <pose>Unspecified</pose>
    <truncated>0</truncated>
    <difficult>0</difficult>
    <bndbox>
      <xmin>108</xmin>
      <ymin>688</ymin>
      <xmax>1137</xmax>
      <ymax>1633</ymax>
    </bndbox>
  </object>
  <object>
    <name>d10_3</name>
    <pose>Unspecified</pose>
    <truncated>0</truncated>
    <difficult>0</difficult>
    <bndbox>
      <xmin>1540</xmin>
      <ymin>637</ymin>
      <xmax>2435</xmax>
      <ymax>1620</ymax>
    </bndbox>
  </object>
  <object>
    <name>d10_3</name>
    <pose>Unspecified</pose>
    <truncated>0</truncated>
    <difficult>0</difficult>
    <bndbox>
      <xmin>2923</xmin>
      <ymin>615</ymin>
      <xmax>3943</xmax>
      <ymax>1595</ymax>
    </bndbox>
  </object>
</annotation>
