<annotation>
  <folder>input</folder>
  <filename>20190405_140659.jpg</filename>
  <path>D:\Dvision\OpenLabeling\main\input\20190405_140659.jpg</path>
  <source>
    <database>Unknown</database>
  </source>
  <size>
    <width>1960</width>
    <height>4032</height>
    <depth>3</depth>
  </size>
  <segmented>0</segmented>
  <object>
    <name>d10_8</name>
    <pose>Unspecified</pose>
    <truncated>0</truncated>
    <difficult>0</difficult>
    <bndbox>
      <xmin>511</xmin>
      <ymin>32</ymin>
      <xmax>1350</xmax>
      <ymax>1082</ymax>
    </bndbox>
  </object>
  <object>
    <name>d10_8</name>
    <pose>Unspecified</pose>
    <truncated>0</truncated>
    <difficult>0</difficult>
    <bndbox>
      <xmin>552</xmin>
      <ymin>1472</ymin>
      <xmax>1319</xmax>
      <ymax>2601</ymax>
    </bndbox>
  </object>
  <object>
    <name>d10_8</name>
    <pose>Unspecified</pose>
    <truncated>0</truncated>
    <difficult>0</difficult>
    <bndbox>
      <xmin>470</xmin>
      <ymin>2782</ymin>
      <xmax>1317</xmax>
      <ymax>3953</ymax>
    </bndbox>
  </object>
</annotation>
