<annotation>
  <folder>input</folder>
  <filename>20190328_193835.jpg</filename>
  <path>D:\Dvision\OpenLabeling\main\input\20190328_193835.jpg</path>
  <source>
    <database>Unknown</database>
  </source>
  <size>
    <width>4032</width>
    <height>1960</height>
    <depth>3</depth>
  </size>
  <segmented>0</segmented>
  <object>
    <name>d6_4</name>
    <pose>Unspecified</pose>
    <truncated>0</truncated>
    <difficult>0</difficult>
    <bndbox>
      <xmin>141</xmin>
      <ymin>561</ymin>
      <xmax>878</xmax>
      <ymax>1249</ymax>
    </bndbox>
  </object>
  <object>
    <name>d6_4</name>
    <pose>Unspecified</pose>
    <truncated>0</truncated>
    <difficult>0</difficult>
    <bndbox>
      <xmin>1636</xmin>
      <ymin>596</ymin>
      <xmax>2221</xmax>
      <ymax>1297</ymax>
    </bndbox>
  </object>
  <object>
    <name>d6_4</name>
    <pose>Unspecified</pose>
    <truncated>0</truncated>
    <difficult>0</difficult>
    <bndbox>
      <xmin>3124</xmin>
      <ymin>551</ymin>
      <xmax>3866</xmax>
      <ymax>1281</ymax>
    </bndbox>
  </object>
</annotation>
