<annotation>
  <folder>input</folder>
  <filename>DSC_0158.JPG</filename>
  <path>/home/mauro/Workspace/dvision/OpenLabeling/main/input/DSC_0158.JPG</path>
  <source>
    <database>Unknown</database>
  </source>
  <size>
    <width>4208</width>
    <height>3120</height>
    <depth>3</depth>
  </size>
  <segmented>0</segmented>
  <object>
    <name>d100_00</name>
    <pose>Unspecified</pose>
    <truncated>0</truncated>
    <difficult>0</difficult>
    <bndbox>
      <xmin>2599</xmin>
      <ymin>1247</ymin>
      <xmax>3012</xmax>
      <ymax>1673</ymax>
    </bndbox>
  </object>
  <object>
    <name>d100_10</name>
    <pose>Unspecified</pose>
    <truncated>0</truncated>
    <difficult>0</difficult>
    <bndbox>
      <xmin>2980</xmin>
      <ymin>1999</ymin>
      <xmax>3451</xmax>
      <ymax>2448</ymax>
    </bndbox>
  </object>
  <object>
    <name>d100_20</name>
    <pose>Unspecified</pose>
    <truncated>0</truncated>
    <difficult>0</difficult>
    <bndbox>
      <xmin>3678</xmin>
      <ymin>1569</ymin>
      <xmax>4158</xmax>
      <ymax>1963</ymax>
    </bndbox>
  </object>
  <object>
    <name>d100_30</name>
    <pose>Unspecified</pose>
    <truncated>0</truncated>
    <difficult>0</difficult>
    <bndbox>
      <xmin>1041</xmin>
      <ymin>2158</ymin>
      <xmax>1449</xmax>
      <ymax>2580</ymax>
    </bndbox>
  </object>
  <object>
    <name>d100_30</name>
    <pose>Unspecified</pose>
    <truncated>0</truncated>
    <difficult>0</difficult>
    <bndbox>
      <xmin>67</xmin>
      <ymin>1287</ymin>
      <xmax>575</xmax>
      <ymax>1705</ymax>
    </bndbox>
  </object>
  <object>
    <name>d100_40</name>
    <pose>Unspecified</pose>
    <truncated>0</truncated>
    <difficult>0</difficult>
    <bndbox>
      <xmin>1653</xmin>
      <ymin>716</ymin>
      <xmax>2088</xmax>
      <ymax>1142</ymax>
    </bndbox>
  </object>
  <object>
    <name>d100_50</name>
    <pose>Unspecified</pose>
    <truncated>0</truncated>
    <difficult>0</difficult>
    <bndbox>
      <xmin>1639</xmin>
      <ymin>1442</ymin>
      <xmax>2060</xmax>
      <ymax>1859</ymax>
    </bndbox>
  </object>
  <object>
    <name>d100_50</name>
    <pose>Unspecified</pose>
    <truncated>0</truncated>
    <difficult>0</difficult>
    <bndbox>
      <xmin>3587</xmin>
      <ymin>589</ymin>
      <xmax>4044</xmax>
      <ymax>1024</ymax>
    </bndbox>
  </object>
  <object>
    <name>d100_60</name>
    <pose>Unspecified</pose>
    <truncated>0</truncated>
    <difficult>0</difficult>
    <bndbox>
      <xmin>326</xmin>
      <ymin>226</ymin>
      <xmax>765</xmax>
      <ymax>689</ymax>
    </bndbox>
  </object>
  <object>
    <name>d100_80</name>
    <pose>Unspecified</pose>
    <truncated>0</truncated>
    <difficult>0</difficult>
    <bndbox>
      <xmin>1834</xmin>
      <ymin>2471</ymin>
      <xmax>2264</xmax>
      <ymax>2915</ymax>
    </bndbox>
  </object>
</annotation>
