<annotation>
  <folder>input</folder>
  <filename>DSC_0243.JPG</filename>
  <path>/home/mauro/Workspace/dvision/OpenLabeling/main/input/DSC_0243.JPG</path>
  <source>
    <database>Unknown</database>
  </source>
  <size>
    <width>4208</width>
    <height>3120</height>
    <depth>3</depth>
  </size>
  <segmented>0</segmented>
  <object>
    <name>d100_00</name>
    <pose>Unspecified</pose>
    <truncated>0</truncated>
    <difficult>0</difficult>
    <bndbox>
      <xmin>3641</xmin>
      <ymin>1745</ymin>
      <xmax>4180</xmax>
      <ymax>2258</ymax>
    </bndbox>
  </object>
  <object>
    <name>d100_00</name>
    <pose>Unspecified</pose>
    <truncated>0</truncated>
    <difficult>0</difficult>
    <bndbox>
      <xmin>217</xmin>
      <ymin>1986</ymin>
      <xmax>715</xmax>
      <ymax>2512</ymax>
    </bndbox>
  </object>
  <object>
    <name>d100_00</name>
    <pose>Unspecified</pose>
    <truncated>0</truncated>
    <difficult>0</difficult>
    <bndbox>
      <xmin>688</xmin>
      <ymin>1315</ymin>
      <xmax>1159</xmax>
      <ymax>1836</ymax>
    </bndbox>
  </object>
  <object>
    <name>d100_10</name>
    <pose>Unspecified</pose>
    <truncated>0</truncated>
    <difficult>0</difficult>
    <bndbox>
      <xmin>2518</xmin>
      <ymin>1197</ymin>
      <xmax>3025</xmax>
      <ymax>1718</ymax>
    </bndbox>
  </object>
  <object>
    <name>d100_20</name>
    <pose>Unspecified</pose>
    <truncated>0</truncated>
    <difficult>0</difficult>
    <bndbox>
      <xmin>3528</xmin>
      <ymin>793</ymin>
      <xmax>4108</xmax>
      <ymax>1292</ymax>
    </bndbox>
  </object>
  <object>
    <name>d100_20</name>
    <pose>Unspecified</pose>
    <truncated>0</truncated>
    <difficult>0</difficult>
    <bndbox>
      <xmin>3039</xmin>
      <ymin>2285</ymin>
      <xmax>3551</xmax>
      <ymax>2875</ymax>
    </bndbox>
  </object>
  <object>
    <name>d100_40</name>
    <pose>Unspecified</pose>
    <truncated>0</truncated>
    <difficult>0</difficult>
    <bndbox>
      <xmin>1974</xmin>
      <ymin>172</ymin>
      <xmax>2409</xmax>
      <ymax>743</ymax>
    </bndbox>
  </object>
  <object>
    <name>d100_40</name>
    <pose>Unspecified</pose>
    <truncated>0</truncated>
    <difficult>0</difficult>
    <bndbox>
      <xmin>1440</xmin>
      <ymin>1070</ymin>
      <xmax>1952</xmax>
      <ymax>1546</ymax>
    </bndbox>
  </object>
  <object>
    <name>d100_90</name>
    <pose>Unspecified</pose>
    <truncated>0</truncated>
    <difficult>0</difficult>
    <bndbox>
      <xmin>1743</xmin>
      <ymin>2099</ymin>
      <xmax>2242</xmax>
      <ymax>2548</ymax>
    </bndbox>
  </object>
  <object>
    <name>d100_80</name>
    <pose>Unspecified</pose>
    <truncated>0</truncated>
    <difficult>0</difficult>
    <bndbox>
      <xmin>221</xmin>
      <ymin>566</ymin>
      <xmax>760</xmax>
      <ymax>1038</ymax>
    </bndbox>
  </object>
</annotation>
