<annotation>
  <folder>input</folder>
  <filename>DSC_0151.JPG</filename>
  <path>/home/mauro/Workspace/DiceScanner/BBlabelTools/OpenLabeling-master/main/input/DSC_0151.JPG</path>
  <source>
    <database>Unknown</database>
  </source>
  <size>
    <width>4208</width>
    <height>3120</height>
    <depth>3</depth>
  </size>
  <segmented>0</segmented>
  <object>
    <name>d10</name>
    <pose>Unspecified</pose>
    <truncated>0</truncated>
    <difficult>0</difficult>
    <bndbox>
      <xmin>1571</xmin>
      <ymin>66</ymin>
      <xmax>1940</xmax>
      <ymax>532</ymax>
    </bndbox>
  </object>
  <object>
    <name>d10</name>
    <pose>Unspecified</pose>
    <truncated>0</truncated>
    <difficult>0</difficult>
    <bndbox>
      <xmin>882</xmin>
      <ymin>536</ymin>
      <xmax>1298</xmax>
      <ymax>929</ymax>
    </bndbox>
  </object>
  <object>
    <name>d10</name>
    <pose>Unspecified</pose>
    <truncated>0</truncated>
    <difficult>0</difficult>
    <bndbox>
      <xmin>316</xmin>
      <ymin>1601</ymin>
      <xmax>762</xmax>
      <ymax>2011</ymax>
    </bndbox>
  </object>
  <object>
    <name>d10</name>
    <pose>Unspecified</pose>
    <truncated>0</truncated>
    <difficult>0</difficult>
    <bndbox>
      <xmin>2706</xmin>
      <ymin>299</ymin>
      <xmax>3099</xmax>
      <ymax>739</ymax>
    </bndbox>
  </object>
  <object>
    <name>d10</name>
    <pose>Unspecified</pose>
    <truncated>0</truncated>
    <difficult>0</difficult>
    <bndbox>
      <xmin>3245</xmin>
      <ymin>1082</ymin>
      <xmax>3685</xmax>
      <ymax>1515</ymax>
    </bndbox>
  </object>
  <object>
    <name>d10</name>
    <pose>Unspecified</pose>
    <truncated>0</truncated>
    <difficult>0</difficult>
    <bndbox>
      <xmin>3232</xmin>
      <ymin>1864</ymin>
      <xmax>3728</xmax>
      <ymax>2244</ymax>
    </bndbox>
  </object>
  <object>
    <name>d10</name>
    <pose>Unspecified</pose>
    <truncated>0</truncated>
    <difficult>0</difficult>
    <bndbox>
      <xmin>2243</xmin>
      <ymin>1058</ymin>
      <xmax>2596</xmax>
      <ymax>1495</ymax>
    </bndbox>
  </object>
  <object>
    <name>d10</name>
    <pose>Unspecified</pose>
    <truncated>0</truncated>
    <difficult>0</difficult>
    <bndbox>
      <xmin>2320</xmin>
      <ymin>2011</ymin>
      <xmax>2716</xmax>
      <ymax>2467</ymax>
    </bndbox>
  </object>
  <object>
    <name>d10</name>
    <pose>Unspecified</pose>
    <truncated>0</truncated>
    <difficult>0</difficult>
    <bndbox>
      <xmin>1468</xmin>
      <ymin>1641</ymin>
      <xmax>1854</xmax>
      <ymax>2054</ymax>
    </bndbox>
  </object>
  <object>
    <name>d10</name>
    <pose>Unspecified</pose>
    <truncated>0</truncated>
    <difficult>0</difficult>
    <bndbox>
      <xmin>1178</xmin>
      <ymin>2390</ymin>
      <xmax>1554</xmax>
      <ymax>2820</ymax>
    </bndbox>
  </object>
</annotation>
