<annotation>
  <folder>input</folder>
  <filename>20190331_171609.jpg</filename>
  <path>D:\Dvision\OpenLabeling\main\input\20190331_171609.jpg</path>
  <source>
    <database>Unknown</database>
  </source>
  <size>
    <width>1960</width>
    <height>4032</height>
    <depth>3</depth>
  </size>
  <segmented>0</segmented>
  <object>
    <name>d12_12</name>
    <pose>Unspecified</pose>
    <truncated>0</truncated>
    <difficult>0</difficult>
    <bndbox>
      <xmin>343</xmin>
      <ymin>76</ymin>
      <xmax>1219</xmax>
      <ymax>1179</ymax>
    </bndbox>
  </object>
  <object>
    <name>d12_12</name>
    <pose>Unspecified</pose>
    <truncated>0</truncated>
    <difficult>0</difficult>
    <bndbox>
      <xmin>327</xmin>
      <ymin>1435</ymin>
      <xmax>1272</xmax>
      <ymax>2480</ymax>
    </bndbox>
  </object>
  <object>
    <name>d12_12</name>
    <pose>Unspecified</pose>
    <truncated>0</truncated>
    <difficult>0</difficult>
    <bndbox>
      <xmin>419</xmin>
      <ymin>2919</ymin>
      <xmax>1313</xmax>
      <ymax>3933</ymax>
    </bndbox>
  </object>
</annotation>
