<annotation>
  <folder>input</folder>
  <filename>20190328_205835.jpg</filename>
  <path>D:\Dvision\OpenLabeling\main\input\20190328_205835.jpg</path>
  <source>
    <database>Unknown</database>
  </source>
  <size>
    <width>4032</width>
    <height>1960</height>
    <depth>3</depth>
  </size>
  <segmented>0</segmented>
  <object>
    <name>d8_7</name>
    <pose>Unspecified</pose>
    <truncated>0</truncated>
    <difficult>0</difficult>
    <bndbox>
      <xmin>3189</xmin>
      <ymin>526</ymin>
      <xmax>4007</xmax>
      <ymax>1233</ymax>
    </bndbox>
  </object>
  <object>
    <name>d8_7</name>
    <pose>Unspecified</pose>
    <truncated>0</truncated>
    <difficult>0</difficult>
    <bndbox>
      <xmin>1693</xmin>
      <ymin>532</ymin>
      <xmax>2620</xmax>
      <ymax>1347</ymax>
    </bndbox>
  </object>
  <object>
    <name>d8_7</name>
    <pose>Unspecified</pose>
    <truncated>0</truncated>
    <difficult>0</difficult>
    <bndbox>
      <xmin>100</xmin>
      <ymin>580</ymin>
      <xmax>1056</xmax>
      <ymax>1373</ymax>
    </bndbox>
  </object>
</annotation>
