<annotation>
  <folder>input</folder>
  <filename>20190405_140155.jpg</filename>
  <path>D:\Dvision\OpenLabeling\main\input\20190405_140155.jpg</path>
  <source>
    <database>Unknown</database>
  </source>
  <size>
    <width>4032</width>
    <height>1960</height>
    <depth>3</depth>
  </size>
  <segmented>0</segmented>
  <object>
    <name>d10_8</name>
    <pose>Unspecified</pose>
    <truncated>0</truncated>
    <difficult>0</difficult>
    <bndbox>
      <xmin>84</xmin>
      <ymin>520</ymin>
      <xmax>1217</xmax>
      <ymax>1433</ymax>
    </bndbox>
  </object>
  <object>
    <name>d10_8</name>
    <pose>Unspecified</pose>
    <truncated>0</truncated>
    <difficult>0</difficult>
    <bndbox>
      <xmin>1540</xmin>
      <ymin>494</ymin>
      <xmax>2588</xmax>
      <ymax>1462</ymax>
    </bndbox>
  </object>
  <object>
    <name>d10_8</name>
    <pose>Unspecified</pose>
    <truncated>0</truncated>
    <difficult>0</difficult>
    <bndbox>
      <xmin>2947</xmin>
      <ymin>475</ymin>
      <xmax>3995</xmax>
      <ymax>1420</ymax>
    </bndbox>
  </object>
</annotation>
